[
  {
    "n": 1,
    "file": "education_0001.jpg",
    "path": "images\\thumbs\\education\\education_0001.jpg",
    "src_url": "https://www.flickr.com/photos/60455048@N02/27441094991",
    "source": "openverse",
    "license": "pdm",
    "creator": "Queensland State Archives",
    "keyword": "",
    "cat": "education",
    "harvested": "2026-04-22T15:34:36"
  },
  {
    "n": 2,
    "file": "education_0002.jpg",
    "path": "images\\thumbs\\education\\education_0002.jpg",
    "src_url": "https://www.flickr.com/photos/124218704@N03/26679273853",
    "source": "openverse",
    "license": "by-sa",
    "creator": "SIM USA",
    "keyword": "",
    "cat": "education",
    "harvested": "2026-04-22T15:34:37"
  },
  {
    "n": 3,
    "file": "education_0003.jpg",
    "path": "images\\thumbs\\education\\education_0003.jpg",
    "src_url": "https://www.flickr.com/photos/29155878@N03/17990211551",
    "source": "openverse",
    "license": "cc0",
    "creator": "Open Grid Scheduler / Grid Engine",
    "keyword": "",
    "cat": "education",
    "harvested": "2026-04-22T15:34:38"
  },
  {
    "n": 4,
    "file": "education_0004.jpg",
    "path": "images\\thumbs\\education\\education_0004.jpg",
    "src_url": "https://www.flickr.com/photos/90729502@N05/29428436431",
    "source": "openverse",
    "license": "by",
    "creator": "Vandy CFT",
    "keyword": "",
    "cat": "education",
    "harvested": "2026-04-22T15:34:40"
  },
  {
    "n": 5,
    "file": "education_0005.jpg",
    "path": "images\\thumbs\\education\\education_0005.jpg",
    "src_url": "https://www.flickr.com/photos/83633410@N07/7658268052",
    "source": "openverse",
    "license": "by-sa",
    "creator": "CollegeDegrees360",
    "keyword": "",
    "cat": "education",
    "harvested": "2026-04-22T15:34:41"
  },
  {
    "n": 6,
    "file": "education_0006.jpg",
    "path": "images\\thumbs\\education\\education_0006.jpg",
    "src_url": "https://www.flickr.com/photos/48445211@N06/14267010583",
    "source": "openverse",
    "license": "by",
    "creator": "US Department of Education",
    "keyword": "",
    "cat": "education",
    "harvested": "2026-04-22T15:34:42"
  },
  {
    "n": 7,
    "file": "education_0007.jpg",
    "path": "images\\thumbs\\education\\education_0007.jpg",
    "src_url": "https://www.flickr.com/photos/47823583@N03/5762453888",
    "source": "openverse",
    "license": "by",
    "creator": "Enokson",
    "keyword": "",
    "cat": "education",
    "harvested": "2026-04-22T15:34:43"
  },
  {
    "n": 8,
    "file": "education_0008.jpg",
    "path": "images\\thumbs\\education\\education_0008.jpg",
    "src_url": "https://www.flickr.com/photos/16199531@N00/6012672577",
    "source": "openverse",
    "license": "by-nd",
    "creator": "Ed Passi ©",
    "keyword": "",
    "cat": "education",
    "harvested": "2026-04-22T15:34:44"
  },
  {
    "n": 9,
    "file": "education_0009.jpg",
    "path": "images\\thumbs\\education\\education_0009.jpg",
    "src_url": "https://www.flickr.com/photos/47823583@N03/5762454084",
    "source": "openverse",
    "license": "by",
    "creator": "Enokson",
    "keyword": "",
    "cat": "education",
    "harvested": "2026-04-22T15:34:45"
  },
  {
    "n": 10,
    "file": "education_0010.jpg",
    "path": "images\\thumbs\\education\\education_0010.jpg",
    "src_url": "https://www.flickr.com/photos/41431665@N07/9665507040",
    "source": "openverse",
    "license": "by",
    "creator": "COD Newsroom",
    "keyword": "",
    "cat": "education",
    "harvested": "2026-04-22T15:34:47"
  },
  {
    "n": 11,
    "file": "education_0011.jpg",
    "path": "images\\thumbs\\education\\education_0011.jpg",
    "src_url": "https://www.flickr.com/photos/41431665@N07/9662223153",
    "source": "openverse",
    "license": "by",
    "creator": "COD Newsroom",
    "keyword": "",
    "cat": "education",
    "harvested": "2026-04-22T15:34:48"
  },
  {
    "n": 12,
    "file": "education_0012.jpg",
    "path": "images\\thumbs\\education\\education_0012.jpg",
    "src_url": "https://www.flickr.com/photos/95639384@N08/8720604364",
    "source": "openverse",
    "license": "by-sa",
    "creator": "Lupuca",
    "keyword": "",
    "cat": "education",
    "harvested": "2026-04-22T15:34:50"
  },
  {
    "n": 13,
    "file": "education_0013.jpg",
    "path": "images\\thumbs\\education\\education_0013.jpg",
    "src_url": "https://www.flickr.com/photos/73645804@N00/4121373286",
    "source": "openverse",
    "license": "by",
    "creator": "woodleywonderworks",
    "keyword": "",
    "cat": "education",
    "harvested": "2026-04-22T15:34:52"
  },
  {
    "n": 14,
    "file": "education_0014.jpg",
    "path": "images\\thumbs\\education\\education_0014.jpg",
    "src_url": "https://www.flickr.com/photos/107445583@N04/16578087888",
    "source": "openverse",
    "license": "by",
    "creator": "Street Photography candid",
    "keyword": "",
    "cat": "education",
    "harvested": "2026-04-22T15:34:53"
  },
  {
    "n": 15,
    "file": "education_0015.jpg",
    "path": "images\\thumbs\\education\\education_0015.jpg",
    "src_url": "https://www.flickr.com/photos/69031678@N00/6416178725",
    "source": "openverse",
    "license": "by",
    "creator": "ToGa Wanderings",
    "keyword": "",
    "cat": "education",
    "harvested": "2026-04-22T15:34:55"
  },
  {
    "n": 16,
    "file": "education_0016.jpg",
    "path": "images\\thumbs\\education\\education_0016.jpg",
    "src_url": "https://www.flickr.com/photos/57280691@N02/5843577306",
    "source": "openverse",
    "license": "by",
    "creator": "albertogp123",
    "keyword": "",
    "cat": "education",
    "harvested": "2026-04-22T15:34:55"
  },
  {
    "n": 17,
    "file": "education_0017.jpg",
    "path": "images\\thumbs\\education\\education_0017.jpg",
    "src_url": "https://www.flickr.com/photos/73645804@N00/7170098685",
    "source": "openverse",
    "license": "by",
    "creator": "woodleywonderworks",
    "keyword": "",
    "cat": "education",
    "harvested": "2026-04-22T15:34:56"
  },
  {
    "n": 18,
    "file": "education_0018.jpg",
    "path": "images\\thumbs\\education\\education_0018.jpg",
    "src_url": "https://www.flickr.com/photos/51607907@N03/6082291735",
    "source": "openverse",
    "license": "by-sa",
    "creator": "barbourians",
    "keyword": "",
    "cat": "education",
    "harvested": "2026-04-22T15:34:58"
  },
  {
    "n": 19,
    "file": "education_0019.jpg",
    "path": "images\\thumbs\\education\\education_0019.jpg",
    "src_url": "https://www.flickr.com/photos/41087714@N00/253197253",
    "source": "openverse",
    "license": "by",
    "creator": "Rex Pe",
    "keyword": "",
    "cat": "education",
    "harvested": "2026-04-22T15:34:59"
  },
  {
    "n": 20,
    "file": "education_0020.jpg",
    "path": "images\\thumbs\\education\\education_0020.jpg",
    "src_url": "https://www.flickr.com/photos/73645804@N00/4005631298",
    "source": "openverse",
    "license": "by",
    "creator": "woodleywonderworks",
    "keyword": "",
    "cat": "education",
    "harvested": "2026-04-22T15:35:01"
  },
  {
    "n": 21,
    "file": "education_0021.jpg",
    "path": "images\\thumbs\\education\\education_0021.jpg",
    "src_url": "https://www.flickr.com/photos/86314613@N08/7899419760",
    "source": "openverse",
    "license": "by",
    "creator": "samstockton",
    "keyword": "",
    "cat": "education",
    "harvested": "2026-04-22T15:35:02"
  },
  {
    "n": 22,
    "file": "education_0022.jpg",
    "path": "images\\thumbs\\education\\education_0022.jpg",
    "src_url": "https://www.flickr.com/photos/79427691@N00/6695935031",
    "source": "openverse",
    "license": "by",
    "creator": "Barrett Web Coordinator",
    "keyword": "",
    "cat": "education",
    "harvested": "2026-04-22T15:35:03"
  },
  {
    "n": 23,
    "file": "education_0023.jpg",
    "path": "images\\thumbs\\education\\education_0023.jpg",
    "src_url": "https://www.flickr.com/photos/24662369@N07/3465277735",
    "source": "openverse",
    "license": "by",
    "creator": "NASA Goddard Photo and Video",
    "keyword": "",
    "cat": "education",
    "harvested": "2026-04-22T15:35:04"
  },
  {
    "n": 24,
    "file": "education_0024.jpg",
    "path": "images\\thumbs\\education\\education_0024.jpg",
    "src_url": "https://www.flickr.com/photos/69124018@N03/8066863117",
    "source": "openverse",
    "license": "by",
    "creator": "wecometolearn",
    "keyword": "",
    "cat": "education",
    "harvested": "2026-04-22T15:35:05"
  },
  {
    "n": 25,
    "file": "education_0025.jpg",
    "path": "images\\thumbs\\education\\education_0025.jpg",
    "src_url": "https://www.flickr.com/photos/73645804@N00/5112989556",
    "source": "openverse",
    "license": "by",
    "creator": "woodleywonderworks",
    "keyword": "",
    "cat": "education",
    "harvested": "2026-04-22T15:35:06"
  },
  {
    "n": 26,
    "file": "education_0026.jpg",
    "path": "images\\thumbs\\education\\education_0026.jpg",
    "src_url": "https://www.flickr.com/photos/38445726@N04/5278030021",
    "source": "openverse",
    "license": "by",
    "creator": "Kheel Center, Cornell University Library",
    "keyword": "",
    "cat": "education",
    "harvested": "2026-04-22T15:35:07"
  },
  {
    "n": 27,
    "file": "education_0027.jpg",
    "path": "images\\thumbs\\education\\education_0027.jpg",
    "src_url": "https://www.flickr.com/photos/24662369@N07/3466091238",
    "source": "openverse",
    "license": "by",
    "creator": "NASA Goddard Photo and Video",
    "keyword": "",
    "cat": "education",
    "harvested": "2026-04-22T15:35:09"
  },
  {
    "n": 28,
    "file": "education_0028.jpg",
    "path": "images\\thumbs\\education\\education_0028.jpg",
    "src_url": "https://www.flickr.com/photos/79427691@N00/6695932871",
    "source": "openverse",
    "license": "by",
    "creator": "Barrett Web Coordinator",
    "keyword": "",
    "cat": "education",
    "harvested": "2026-04-22T15:35:10"
  },
  {
    "n": 29,
    "file": "education_0029.jpg",
    "path": "images\\thumbs\\education\\education_0029.jpg",
    "src_url": "https://www.flickr.com/photos/24662369@N07/3466091936",
    "source": "openverse",
    "license": "by",
    "creator": "NASA Goddard Photo and Video",
    "keyword": "",
    "cat": "education",
    "harvested": "2026-04-22T15:35:11"
  },
  {
    "n": 30,
    "file": "education_0030.jpg",
    "path": "images\\thumbs\\education\\education_0030.jpg",
    "src_url": "https://www.flickr.com/photos/24662369@N07/3466092408",
    "source": "openverse",
    "license": "by",
    "creator": "NASA Goddard Photo and Video",
    "keyword": "",
    "cat": "education",
    "harvested": "2026-04-22T15:35:13"
  },
  {
    "n": 31,
    "file": "education_0031.jpg",
    "path": "images\\thumbs\\education\\education_0031.jpg",
    "src_url": "https://www.flickr.com/photos/24662369@N07/3465279329",
    "source": "openverse",
    "license": "by",
    "creator": "NASA Goddard Photo and Video",
    "keyword": "",
    "cat": "education",
    "harvested": "2026-04-22T15:35:14"
  },
  {
    "n": 32,
    "file": "education_0032.jpg",
    "path": "images\\thumbs\\education\\education_0032.jpg",
    "src_url": "https://www.flickr.com/photos/44124348109@N01/15105407149",
    "source": "openverse",
    "license": "by",
    "creator": "jurvetson",
    "keyword": "",
    "cat": "education",
    "harvested": "2026-04-22T15:35:15"
  },
  {
    "n": 33,
    "file": "education_0033.jpg",
    "path": "images\\thumbs\\education\\education_0033.jpg",
    "src_url": "https://www.flickr.com/photos/68288285@N00/521921493",
    "source": "openverse",
    "license": "by-sa",
    "creator": "Aka Hige",
    "keyword": "",
    "cat": "education",
    "harvested": "2026-04-22T15:35:16"
  },
  {
    "n": 34,
    "file": "education_0034.jpg",
    "path": "images\\thumbs\\education\\education_0034.jpg",
    "src_url": "https://www.flickr.com/photos/41087714@N00/250121794",
    "source": "openverse",
    "license": "by",
    "creator": "Rex Pe",
    "keyword": "",
    "cat": "education",
    "harvested": "2026-04-22T15:35:18"
  },
  {
    "n": 35,
    "file": "education_0035.jpg",
    "path": "images\\thumbs\\education\\education_0035.jpg",
    "src_url": "https://www.flickr.com/photos/73645804@N00/2458666314",
    "source": "openverse",
    "license": "by",
    "creator": "woodleywonderworks",
    "keyword": "",
    "cat": "education",
    "harvested": "2026-04-22T15:35:19"
  },
  {
    "n": 36,
    "file": "education_0036.jpg",
    "path": "images\\thumbs\\education\\education_0036.jpg",
    "src_url": "https://www.flickr.com/photos/50169152@N06/15217469952",
    "source": "openverse",
    "license": "by",
    "creator": "BLM Oregon & Washington",
    "keyword": "",
    "cat": "education",
    "harvested": "2026-04-22T15:35:20"
  },
  {
    "n": 37,
    "file": "education_0037.jpg",
    "path": "images\\thumbs\\education\\education_0037.jpg",
    "src_url": "https://www.flickr.com/photos/115089924@N02/12212474014",
    "source": "openverse",
    "license": "by",
    "creator": "www.ilmicrofono.it",
    "keyword": "",
    "cat": "education",
    "harvested": "2026-04-22T15:35:21"
  },
  {
    "n": 38,
    "file": "education_0038.jpg",
    "path": "images\\thumbs\\education\\education_0038.jpg",
    "src_url": "https://www.flickr.com/photos/73645804@N00/2923015579",
    "source": "openverse",
    "license": "by",
    "creator": "woodleywonderworks",
    "keyword": "",
    "cat": "education",
    "harvested": "2026-04-22T15:35:22"
  },
  {
    "n": 39,
    "file": "education_0039.jpg",
    "path": "images\\thumbs\\education\\education_0039.jpg",
    "src_url": "https://www.flickr.com/photos/79427691@N00/9042426712",
    "source": "openverse",
    "license": "by",
    "creator": "Barrett Web Coordinator",
    "keyword": "",
    "cat": "education",
    "harvested": "2026-04-22T15:35:24"
  },
  {
    "n": 40,
    "file": "education_0040.jpg",
    "path": "images\\thumbs\\education\\education_0040.jpg",
    "src_url": "https://www.flickr.com/photos/79427691@N00/9042427296",
    "source": "openverse",
    "license": "by",
    "creator": "Barrett Web Coordinator",
    "keyword": "",
    "cat": "education",
    "harvested": "2026-04-22T15:35:26"
  },
  {
    "n": 41,
    "file": "education_0041.jpg",
    "path": "images\\thumbs\\education\\education_0041.jpg",
    "src_url": "https://www.flickr.com/photos/34608255@N08/10056355054",
    "source": "openverse",
    "license": "by",
    "creator": "The City of Toronto",
    "keyword": "",
    "cat": "education",
    "harvested": "2026-04-22T15:35:27"
  },
  {
    "n": 42,
    "file": "education_0042.jpg",
    "path": "images\\thumbs\\education\\education_0042.jpg",
    "src_url": "https://www.flickr.com/photos/36768983@N06/4474421855",
    "source": "openverse",
    "license": "by",
    "creator": "shutterhacks",
    "keyword": "",
    "cat": "education",
    "harvested": "2026-04-22T15:35:28"
  },
  {
    "n": 43,
    "file": "education_0043.jpg",
    "path": "images\\thumbs\\education\\education_0043.jpg",
    "src_url": "https://www.flickr.com/photos/38146962@N00/900888676",
    "source": "openverse",
    "license": "by-sa",
    "creator": "Chor Ip",
    "keyword": "",
    "cat": "education",
    "harvested": "2026-04-22T15:35:29"
  },
  {
    "n": 44,
    "file": "education_0044.jpg",
    "path": "images\\thumbs\\education\\education_0044.jpg",
    "src_url": "https://www.flickr.com/photos/25754837@N00/376152628",
    "source": "openverse",
    "license": "by-sa",
    "creator": "timetrax23",
    "keyword": "",
    "cat": "education",
    "harvested": "2026-04-22T15:35:30"
  },
  {
    "n": 45,
    "file": "education_0045.jpg",
    "path": "images\\thumbs\\education\\education_0045.jpg",
    "src_url": "https://www.flickr.com/photos/29817792@N08/4131076475",
    "source": "openverse",
    "license": "by",
    "creator": "CCAC North Library",
    "keyword": "",
    "cat": "education",
    "harvested": "2026-04-22T15:35:31"
  },
  {
    "n": 46,
    "file": "education_0046.jpg",
    "path": "images\\thumbs\\education\\education_0046.jpg",
    "src_url": "https://www.flickr.com/photos/45553145@N00/1778980935",
    "source": "openverse",
    "license": "by",
    "creator": "chillihead",
    "keyword": "",
    "cat": "education",
    "harvested": "2026-04-22T15:35:32"
  },
  {
    "n": 47,
    "file": "education_0047.jpg",
    "path": "images\\thumbs\\education\\education_0047.jpg",
    "src_url": "https://www.flickr.com/photos/8489692@N03/5020407401",
    "source": "openverse",
    "license": "by",
    "creator": "katerha",
    "keyword": "",
    "cat": "education",
    "harvested": "2026-04-22T15:35:33"
  },
  {
    "n": 48,
    "file": "education_0048.jpg",
    "path": "images\\thumbs\\education\\education_0048.jpg",
    "src_url": "https://www.flickr.com/photos/12037949632@N01/99129170",
    "source": "openverse",
    "license": "by",
    "creator": "Stewart",
    "keyword": "",
    "cat": "education",
    "harvested": "2026-04-22T15:35:34"
  },
  {
    "n": 49,
    "file": "education_0049.jpg",
    "path": "images\\thumbs\\education\\education_0049.jpg",
    "src_url": "https://www.flickr.com/photos/61132483@N00/6975024540",
    "source": "openverse",
    "license": "by",
    "creator": "Elsie esq.",
    "keyword": "",
    "cat": "education",
    "harvested": "2026-04-22T15:35:35"
  },
  {
    "n": 50,
    "file": "education_0050.jpg",
    "path": "images\\thumbs\\education\\education_0050.jpg",
    "src_url": "https://www.flickr.com/photos/10485077@N06/7167897339",
    "source": "openverse",
    "license": "by",
    "creator": "edenpictures",
    "keyword": "",
    "cat": "education",
    "harvested": "2026-04-22T15:35:37"
  },
  {
    "n": 51,
    "file": "education_0051.jpg",
    "path": "images\\thumbs\\education\\education_0051.jpg",
    "src_url": "https://www.flickr.com/photos/128617711@N04/16261062360",
    "source": "openverse",
    "license": "by",
    "creator": "University of Macedonia-uom.gr",
    "keyword": "",
    "cat": "education",
    "harvested": "2026-04-22T15:35:38"
  },
  {
    "n": 52,
    "file": "education_0052.jpg",
    "path": "images\\thumbs\\education\\education_0052.jpg",
    "src_url": "https://www.flickr.com/photos/45256566@N04/8314929977",
    "source": "openverse",
    "license": "by",
    "creator": "Abee5",
    "keyword": "",
    "cat": "education",
    "harvested": "2026-04-22T15:35:39"
  },
  {
    "n": 53,
    "file": "education_0053.jpg",
    "path": "images\\thumbs\\education\\education_0053.jpg",
    "src_url": "https://www.flickr.com/photos/44124368329@N01/2382181451",
    "source": "openverse",
    "license": "by",
    "creator": "david.orban",
    "keyword": "",
    "cat": "education",
    "harvested": "2026-04-22T15:35:40"
  },
  {
    "n": 54,
    "file": "education_0054.jpg",
    "path": "images\\thumbs\\education\\education_0054.jpg",
    "src_url": "https://www.flickr.com/photos/26719227@N00/13981429180",
    "source": "openverse",
    "license": "by",
    "creator": "Han Cheng Yeh",
    "keyword": "",
    "cat": "education",
    "harvested": "2026-04-22T15:35:43"
  },
  {
    "n": 55,
    "file": "education_0055.jpg",
    "path": "images\\thumbs\\education\\education_0055.jpg",
    "src_url": "https://www.flickr.com/photos/51035743246@N01/1651870",
    "source": "openverse",
    "license": "by-sa",
    "creator": "Dawn Endico",
    "keyword": "",
    "cat": "education",
    "harvested": "2026-04-22T15:35:44"
  },
  {
    "n": 56,
    "file": "education_0056.jpg",
    "path": "images\\thumbs\\education\\education_0056.jpg",
    "src_url": "https://www.flickr.com/photos/25869855@N04/4609212148",
    "source": "openverse",
    "license": "by",
    "creator": "Friar's Balsam",
    "keyword": "",
    "cat": "education",
    "harvested": "2026-04-22T15:35:46"
  },
  {
    "n": 57,
    "file": "education_0057.jpg",
    "path": "images\\thumbs\\education\\education_0057.jpg",
    "src_url": "https://www.flickr.com/photos/25637957@N02/8345885557",
    "source": "openverse",
    "license": "by",
    "creator": "speedoflife",
    "keyword": "",
    "cat": "education",
    "harvested": "2026-04-22T15:35:47"
  },
  {
    "n": 58,
    "file": "education_0058.jpg",
    "path": "images\\thumbs\\education\\education_0058.jpg",
    "src_url": "https://www.flickr.com/photos/10039026@N03/2266388742",
    "source": "openverse",
    "license": "by",
    "creator": "Paul Lowry",
    "keyword": "",
    "cat": "education",
    "harvested": "2026-04-22T15:35:48"
  },
  {
    "n": 59,
    "file": "education_0059.jpg",
    "path": "images\\thumbs\\education\\education_0059.jpg",
    "src_url": "https://www.flickr.com/photos/45795292@N00/2388343729",
    "source": "openverse",
    "license": "by",
    "creator": "brokentrinkets",
    "keyword": "",
    "cat": "education",
    "harvested": "2026-04-22T15:35:49"
  },
  {
    "n": 60,
    "file": "education_0060.jpg",
    "path": "images\\thumbs\\education\\education_0060.jpg",
    "src_url": "https://www.flickr.com/photos/41346951@N05/8597609828",
    "source": "openverse",
    "license": "by",
    "creator": "Thomas Leuthard",
    "keyword": "",
    "cat": "education",
    "harvested": "2026-04-22T15:35:51"
  }
]